terrathon/__init__.py
terrathon/terraform.py
terrathon/terrathon.py
terrathon/utils.py
terrathon-0.2.0.dist-info/LICENSE
terrathon-0.2.0.dist-info/METADATA
terrathon-0.2.0.dist-info/WHEEL
terrathon-0.2.0.dist-info/top_level.txt
terrathon-0.2.0.dist-info/RECORD
